{
  "lastUpdate": "2026-04-25T11:10:11.523Z",
  "files": [
    {
      "name": "israel-alerts.kml",
      "url": "https://raw.githubusercontent.com/TannerTunstall/MapPipeline/main/kmls/israel-alerts.kml",
      "size": 1710,
      "updated": "2026-04-25T11:10:11.463Z"
    },
    {
      "name": "mobilize-events.kml",
      "url": "https://raw.githubusercontent.com/TannerTunstall/MapPipeline/main/kmls/mobilize-events.kml",
      "size": 1502992,
      "updated": "2026-04-25T11:10:08.021Z"
    },
    {
      "name": "safeairspace-warnings.kml",
      "url": "https://raw.githubusercontent.com/TannerTunstall/MapPipeline/main/kmls/safeairspace-warnings.kml",
      "size": 3580533,
      "updated": "2026-04-25T11:10:08.038Z"
    }
  ]
}