{
  "lastUpdate": "2026-03-13T23:44:54.122Z",
  "files": [
    {
      "name": "israel-alerts.kml",
      "url": "https://raw.githubusercontent.com/TannerTunstall/MapPipeline/main/kmls/israel-alerts.kml",
      "size": 21663,
      "updated": "2026-03-13T23:44:47.349Z"
    },
    {
      "name": "mobilize-events.kml",
      "url": "https://raw.githubusercontent.com/TannerTunstall/MapPipeline/main/kmls/mobilize-events.kml",
      "size": 1657375,
      "updated": "2026-03-13T23:44:47.355Z"
    },
    {
      "name": "safeairspace-warnings.kml",
      "url": "https://raw.githubusercontent.com/TannerTunstall/MapPipeline/main/kmls/safeairspace-warnings.kml",
      "size": 3577758,
      "updated": "2026-03-13T23:44:53.917Z"
    }
  ]
}