{
  "lastUpdate": "2026-03-28T13:19:34.290Z",
  "files": [
    {
      "name": "israel-alerts.kml",
      "url": "https://raw.githubusercontent.com/TannerTunstall/MapPipeline/main/kmls/israel-alerts.kml",
      "size": 1710,
      "updated": "2026-03-28T13:19:28.847Z"
    },
    {
      "name": "mobilize-events.kml",
      "url": "https://raw.githubusercontent.com/TannerTunstall/MapPipeline/main/kmls/mobilize-events.kml",
      "size": 1502992,
      "updated": "2026-03-28T13:19:28.850Z"
    },
    {
      "name": "safeairspace-warnings.kml",
      "url": "https://raw.githubusercontent.com/TannerTunstall/MapPipeline/main/kmls/safeairspace-warnings.kml",
      "size": 3580008,
      "updated": "2026-03-28T13:19:33.777Z"
    }
  ]
}