{
  "lastUpdate": "2026-03-27T12:30:10.982Z",
  "files": [
    {
      "name": "israel-alerts.kml",
      "url": "https://raw.githubusercontent.com/TannerTunstall/MapPipeline/main/kmls/israel-alerts.kml",
      "size": 8715,
      "updated": "2026-03-27T12:30:10.932Z"
    },
    {
      "name": "mobilize-events.kml",
      "url": "https://raw.githubusercontent.com/TannerTunstall/MapPipeline/main/kmls/mobilize-events.kml",
      "size": 1502992,
      "updated": "2026-03-27T12:30:09.835Z"
    },
    {
      "name": "safeairspace-warnings.kml",
      "url": "https://raw.githubusercontent.com/TannerTunstall/MapPipeline/main/kmls/safeairspace-warnings.kml",
      "size": 3580008,
      "updated": "2026-03-27T12:30:09.850Z"
    }
  ]
}