{
  "lastUpdate": "2026-04-27T13:55:10.525Z",
  "files": [
    {
      "name": "israel-alerts.kml",
      "url": "https://raw.githubusercontent.com/TannerTunstall/MapPipeline/main/kmls/israel-alerts.kml",
      "size": 1710,
      "updated": "2026-04-27T13:55:10.473Z"
    },
    {
      "name": "mobilize-events.kml",
      "url": "https://raw.githubusercontent.com/TannerTunstall/MapPipeline/main/kmls/mobilize-events.kml",
      "size": 1502992,
      "updated": "2026-04-27T13:55:09.310Z"
    },
    {
      "name": "safeairspace-warnings.kml",
      "url": "https://raw.githubusercontent.com/TannerTunstall/MapPipeline/main/kmls/safeairspace-warnings.kml",
      "size": 3580962,
      "updated": "2026-04-27T13:55:09.326Z"
    }
  ]
}